fast_overlap/__init__.py
fast_overlap/_engine.cp38-win_amd64.pyd
fast_overlap/_version.py
tests/__init__.py
tests/test_overlap.py
fast_overlap-0.5.0.dist-info/METADATA
fast_overlap-0.5.0.dist-info/WHEEL
fast_overlap-0.5.0.dist-info/top_level.txt
fast_overlap-0.5.0.dist-info/RECORD
