Metadata-Version: 2.1
Name: fast_overlap
Version: 0.5.0
Home-page: https://github.com/Hekstra-Lab/fast_overlap
Author: Ian Hunt-Isaak, John Russell
Author-email: ianhuntisaak@g.harvard.edu, johnrussell@g.harvard.edu
License: BSD 3-Clause License
Platform: Linux
Platform: Mac OS X
Platform: Windows
Requires-Python: <3.11,>=3.7
Provides-Extra: test
